calib_rt/__init__.py
calib_rt/calib_rt.py
calib_rt/datasets.py
calib_rt/regression.py
calib_rt/screen.py
calib_rt/utils.py
calib_rt/data/20200505_Evosep_100SPD_SG06-16_MLHeLa_100ng_py8_S2-C1_1_2731.d.npz
calib_rt/data/20200505_Evosep_200SPD_SG06-16_MLHeLa_200ng_py8_S3-A1_1_2737.d.npz
calib_rt/data/20211101_PRO2_LS_04_MA_HeLaSCS_0.2_ngHS_GE2_1_1408.d.npz
calib_rt/data/20211103_PRO2_LS_01_MA_HeLa_200_SDC_NS_RE2_1_1418.d.npz
calib_rt/data/20220714_10ngK562_ZI_500ul60C3cm5min_P1-C1_1_9675.d.npz
calib_rt/data/CMs_Subject3_Lvmid_G10_BG11_1_7560.d.npz
calib_rt/data/SC_HeLa_10min1_Slot1-9_1_807.d.npz
calib_rt/data/SC_HeLa_15min1_Slot1-7_1_805.d.npz
calib_rt/data/fmeierab_T190525_CLL_diaPASEF_04_1979.d.npz
calib_rt/data/fmeierab_T190525_CLL_diaPASEF_40_1965.d.npz
Testpycalib_rt-0.1.3.dist-info/LICENSE
Testpycalib_rt-0.1.3.dist-info/METADATA
Testpycalib_rt-0.1.3.dist-info/WHEEL
Testpycalib_rt-0.1.3.dist-info/top_level.txt
Testpycalib_rt-0.1.3.dist-info/RECORD
